LICENSE
README.md
github_webhooks/__init__.py
github_webhooks/app.py
github_webhooks/handlers/__init__.py
github_webhooks/handlers/default.py
github_webhooks/handlers/ping.py
github_webhooks/handlers/registry.py
github_webhooks/handlers/types.py
github_webhooks/py.typed
github_webhooks/schemas/__init__.py
github_webhooks/schemas/objects.py
github_webhooks/schemas/request.py
github_webhooks/web.py
github_webhooks_framework-0.1.11.dist-info/LICENSE
github_webhooks_framework-0.1.11.dist-info/WHEEL
github_webhooks_framework-0.1.11.dist-info/METADATA
github_webhooks_framework-0.1.11.dist-info/RECORD
